src/pydbpool/__init__.py
src/pydbpool/asyncdbpool.py
src/pydbpool/base.py
src/pydbpool/dbapierrors.py
src/pydbpool/dbapiinterface.py
src/pydbpool/dbconnection.py
src/pydbpool/dbpool.py
src/pydbpool/errors.py
src/pydbpool/extra.py
tests/__init__.py
tests/conftest.py
tests/demo.py
tests/run_tests.py
tests/test_exec_sql.py
tests/async/test_async_mysql.py
tests/async/test_async_postgresql.py
tests/async/test_async_sqlite.py
tests/async/test_async_tidb.py
tests/sync/test_doris.py
tests/sync/test_hive.py
tests/sync/test_impala.py
tests/sync/test_mysql.py
tests/sync/test_oracle.py
tests/sync/test_postgresql.py
tests/sync/test_sqlite.py
tests/sync/test_tidb.py
pydbpool-0.1.4.dist-info/METADATA
pydbpool-0.1.4.dist-info/WHEEL
pydbpool-0.1.4.dist-info/entry_points.txt
pydbpool-0.1.4.dist-info/top_level.txt
pydbpool-0.1.4.dist-info/RECORD
