Metadata-Version: 2.4
Name: pydbpool
Version: 0.1.4
Summary: A high-performance database connection pool for Python
Home-page: https://github.com/yourusername/pydbpool
Author: dylan
Author-email: dylan <cgq2012516@163.com>
License: MIT License
Project-URL: Homepage, https://github.com/yourusername/pydbpool
Project-URL: Documentation, https://pydbpool.readthedocs.io/
Project-URL: Bug Tracker, https://github.com/yourusername/pydbpool/issues
Keywords: database,connection-pool,mysql,postgresql,sqlalchemy,async,thread-safe
Classifier: Development Status :: 4 - Beta
Classifier: Intended Audience :: Developers
Classifier: Topic :: Software Development :: Libraries :: Python Modules
Classifier: Topic :: Database
Classifier: License :: OSI Approved :: MIT License
Classifier: Programming Language :: Python :: 3
Classifier: Programming Language :: Python :: 3.7
Classifier: Programming Language :: Python :: 3.8
Classifier: Programming Language :: Python :: 3.9
Classifier: Programming Language :: Python :: 3.10
Classifier: Programming Language :: Python :: 3.11
Classifier: Programming Language :: Python :: 3.12
Requires-Python: >=3.8
Requires-Dist: typing-extensions>=4.0.0
Provides-Extra: dev
Requires-Dist: pytest>=7.0.0; extra == "dev"
Requires-Dist: pytest-cov>=4.0.0; extra == "dev"
Requires-Dist: black>=23.0.0; extra == "dev"
Requires-Dist: isort>=5.0.0; extra == "dev"
Requires-Dist: mypy>=1.0.0; extra == "dev"
Requires-Dist: flake8>=6.0.0; extra == "dev"
Requires-Dist: tox>=4.0.0; extra == "dev"
Provides-Extra: mysql
Requires-Dist: pymysql>=1.1.0; extra == "mysql"
Provides-Extra: postgresql
Requires-Dist: psycopg2-binary>=2.9.0; extra == "postgresql"
Provides-Extra: sqlite
Provides-Extra: oracle
Requires-Dist: oracledb>=3.1.1; extra == "oracle"
Provides-Extra: sqlserver
Requires-Dist: pyodbc>=4.0.0; extra == "sqlserver"
Provides-Extra: async
Requires-Dist: asyncio>=3.4.3; extra == "async"
Requires-Dist: aiomysql>=0.1.0; extra == "async"
Requires-Dist: asyncpg>=0.25.0; extra == "async"
Provides-Extra: all
Requires-Dist: pymysql>=1.1.0; extra == "all"
Requires-Dist: psycopg2-binary>=2.9.0; extra == "all"
Requires-Dist: oracledb>=3.1.1; extra == "all"
Requires-Dist: pyodbc>=4.0.0; extra == "all"
Requires-Dist: asyncio>=3.4.3; extra == "all"
Requires-Dist: aiomysql>=0.1.0; extra == "all"
Requires-Dist: asyncpg>=0.25.0; extra == "all"
Dynamic: author
Dynamic: home-page
Dynamic: requires-python
